webpage2pdf/__init__.py
webpage2pdf/main.py
webpage2pdf/version.py
webpage2pdf/utils/__init__.py
webpage2pdf/utils/browser.py
webpage2pdf/utils/errors.py
webpage2pdf/utils/pdf.py
webpage2pdf/utils/retry.py
webpage_to_pdf_converter-1.1.0.dist-info/METADATA
webpage_to_pdf_converter-1.1.0.dist-info/WHEEL
webpage_to_pdf_converter-1.1.0.dist-info/entry_points.txt
webpage_to_pdf_converter-1.1.0.dist-info/top_level.txt
webpage_to_pdf_converter-1.1.0.dist-info/RECORD
