Metadata-Version: 2.2
Name: webpage-to-pdf-converter
Version: 1.1.0
Summary: A CLI tool to check URLs and save webpages as PDFs
Author: remixonwin
License: MIT
Classifier: Programming Language :: Python :: 3
Classifier: License :: OSI Approved :: MIT License
Classifier: Operating System :: OS Independent
Requires-Python: >=3.12
Requires-Dist: click
Requires-Dist: requests
Requires-Dist: selenium
Requires-Dist: webdriver_manager
Requires-Dist: Pillow
Provides-Extra: test
Requires-Dist: pytest>=7.0.0; extra == "test"
Requires-Dist: pytest-mock>=3.10.0; extra == "test"
Requires-Dist: responses>=0.23.0; extra == "test"
